{
  "_class": "symbolInstance",
  "do_objectID": "63796B99-52BC-451C-854D-8B64B2C45F28",
  "exportOptions": {
    "_class": "exportOptions",
    "exportFormats": [
    ],
    "includedLayerIds": [
    ],
    "layerOptions": 0,
    "shouldTrim": false
  },
  "frame": {
    "_class": "rect",
    "constrainProportions": false,
    "height": 62,
    "width": 266,
    "x": 0,
    "y": 0
  },
  "horizontalSpacing": 0,
  "isFlippedHorizontal": false,
  "isFlippedVertical": false,
  "isLocked": false,
  "isVisible": true,
  "layerListExpandedType": 0,
  "masterInfluenceEdgeMaxXPadding": 0,
  "masterInfluenceEdgeMaxYPadding": 0,
  "masterInfluenceEdgeMinXPadding": 0,
  "masterInfluenceEdgeMinYPadding": 0,
  "name": "input",
  "nameIsFixed": true,
  "overrides": {
    "361AC8AD-EF13-45B4-98DD-CA68F0555026": {
      "A2858DB7-85A4-4281-8018-D2A15E82C9E8": {
        "symbolID": ""
      }
    },
    "6CBDEB9E-51D1-4579-B293-DA809B2DEC0F": {
      "symbolID": ""
    },
    "7DC91DAF-B28F-4F49-915A-5D4700E86FA7": {
      "symbolID": ""
    }
  },
  "resizingConstraint": 35,
  "resizingType": 0,
  "rotation": 0,
  "shouldBreakMaskChain": false,
  "style": {
    "_class": "style",
    "endDecorationType": 0,
    "miterLimit": 10,
    "startDecorationType": 0
  },
  "symbolID": "C2055B17-E9B8-4AE2-A22D-123C62045075",
  "userInfo": {
    "com.animaapp.stc-sketch-plugin": {
      "kModelPropertiesKey": {
      }
    }
  },
  "verticalSpacing": 0
}